{
    "geometry": {
        "coordinates": [
            -118.10584297941742,
            33.75519725104034
        ],
        "type": "Point"
    },
    "properties": {
        "APPLICATIONREASONDESC": "Change of Ownership",
        "BIDAREA": null,
        "BLLICEXEMPT": "No",
        "CLASSDESC": "Services",
        "COMPANYTYPE": "LLC",
        "CONAME": null,
        "COUNCILDISTRICT": 3,
        "DBANAME": null,
        "EXPDTTM": "2016-09-01T00:00:00.000Z",
        "EXPDTTM_IN": "9/1/2016",
        "FULLNAME": "MUNI-FED ANTEA GROUP ENERGY PARTNERS",
        "GPSX": 6529491.715,
        "GPSY": 1733309.36416667,
        "HOMEBASED": "No",
        "INACTVDTTM": null,
        "INSPECTORNAME": "Aswiege",
        "ISSDTTM": "2012-09-01T00:00:00.000Z",
        "LICCATDESC": "Consulting",
        "LICENSEDTTM": "2012-09-19T00:00:00.000Z",
        "LICENSENO": "BU21231070",
        "LICENSETYPE": "BU",
        "LICSTATUS": "Expired",
        "MILESTONE": "Pre-Collections",
        "MILESTONEDATE": "2016-10-03T00:00:00.000Z",
        "NONPROFIT": null,
        "NUMBOOTHS": null,
        "NUMEMP": 4,
        "NUMSEATS": 0,
        "NUMSELLINGDAYS": null,
        "NUMSTANDS": 0,
        "NUMUNITS": 0,
        "NUMVEH": 0,
        "OBJECTID": 28738,
        "OUTSIDECITY": "No",
        "PRODUCTTYPES": null,
        "PROPERTYTYPE": "COM",
        "SEPEVENTNAME": null,
        "SITELOCATION": "6621 E PACIFIC COAST HWY 280",
        "STATELICNO": null,
        "TYPEOFBUSINESS": "Consulting",
        "ZIP": "90803"
    },
    "type": "Feature"
}