{
    "geometry": {
        "coordinates": [
            -118.18712260967276,
            33.76783417840939
        ],
        "type": "Point"
    },
    "properties": {
        "APPLICATIONREASONDESC": "New License",
        "BIDAREA": "DOWNTOWN",
        "BLLICEXEMPT": "No",
        "CLASSDESC": "Services",
        "COMPANYTYPE": "SOLE",
        "CONAME": null,
        "COUNCILDISTRICT": 2,
        "DBANAME": "HEXOLGIC",
        "EXPDTTM": "2013-06-18T00:00:00.000Z",
        "EXPDTTM_IN": "6/18/2013",
        "FULLNAME": "BRENDA GARCIA",
        "GPSX": 6504792.3,
        "GPSY": 1737944.31,
        "HOMEBASED": "No",
        "INACTVDTTM": "2013-06-18T00:00:00.000Z",
        "INSPECTORNAME": "LOVOSS",
        "ISSDTTM": "2010-06-18T00:00:00.000Z",
        "LICCATDESC": "Business Equipment Repair",
        "LICENSEDTTM": "2010-06-18T00:00:00.000Z",
        "LICENSENO": "BU21019580",
        "LICENSETYPE": "BU",
        "LICSTATUS": "Inactive",
        "MILESTONE": "Closed",
        "MILESTONEDATE": "2013-05-29T00:00:00.000Z",
        "NONPROFIT": null,
        "NUMBOOTHS": null,
        "NUMEMP": 1,
        "NUMSEATS": 0,
        "NUMSELLINGDAYS": null,
        "NUMSTANDS": 0,
        "NUMUNITS": 0,
        "NUMVEH": 0,
        "OBJECTID": 88689,
        "OUTSIDECITY": "No",
        "PRODUCTTYPES": null,
        "PROPERTYTYPE": "COM",
        "SEPEVENTNAME": null,
        "SITELOCATION": "408 E 1ST ST 102",
        "STATELICNO": null,
        "TYPEOFBUSINESS": "Business Equipment Repair",
        "ZIP": "90802"
    },
    "type": "Feature"
}