{
    "geometry": {
        "coordinates": [
            -118.18674164775379,
            33.76793759221494
        ],
        "type": "Point"
    },
    "properties": {
        "APPLICATIONREASONDESC": "New License",
        "BIDAREA": "DOWNTOWN",
        "BLLICEXEMPT": "No",
        "CLASSDESC": "Services",
        "COMPANYTYPE": "SOLE",
        "CONAME": null,
        "COUNCILDISTRICT": 2,
        "DBANAME": "VICTORIOUS BARBER STUDIO",
        "EXPDTTM": "2017-05-24T00:00:00.000Z",
        "EXPDTTM_IN": "5/24/2017",
        "FULLNAME": "VICTORIA RAMIREZ",
        "GPSX": 6504908.16,
        "GPSY": 1737981.73,
        "HOMEBASED": "No",
        "INACTVDTTM": null,
        "INSPECTORNAME": "LOVOSS",
        "ISSDTTM": "2004-05-21T00:00:00.000Z",
        "LICCATDESC": "Barber/Beauty Shop Owner",
        "LICENSEDTTM": "2014-05-02T00:00:00.000Z",
        "LICENSENO": "BU20422958",
        "LICENSETYPE": "BU",
        "LICSTATUS": "Active",
        "MILESTONE": "Renewed",
        "MILESTONEDATE": "2016-09-23T00:00:00.000Z",
        "NONPROFIT": null,
        "NUMBOOTHS": null,
        "NUMEMP": 0,
        "NUMSEATS": 0,
        "NUMSELLINGDAYS": null,
        "NUMSTANDS": 0,
        "NUMUNITS": 0,
        "NUMVEH": 0,
        "OBJECTID": 127601,
        "OUTSIDECITY": "No",
        "PRODUCTTYPES": null,
        "PROPERTYTYPE": "COM",
        "SEPEVENTNAME": null,
        "SITELOCATION": "428 E 1ST ST",
        "STATELICNO": null,
        "TYPEOFBUSINESS": "Barber/Beauty Shop Owner",
        "ZIP": "90802"
    },
    "type": "Feature"
}