{
    "geometry": {
        "coordinates": [
            -118.1527487359632,
            33.76509160344463
        ],
        "type": "Point"
    },
    "properties": {
        "APPLICATIONREASONDESC": "New License",
        "BIDAREA": null,
        "BLLICEXEMPT": "No",
        "CLASSDESC": "Services",
        "COMPANYTYPE": "SOLE",
        "CONAME": null,
        "COUNCILDISTRICT": 3,
        "DBANAME": "INTERNATIONAL NURSE RECRUITERS",
        "EXPDTTM": "2003-08-12T00:00:00.000Z",
        "EXPDTTM_IN": "8/12/2003",
        "FULLNAME": "ROBERT E YOUNG",
        "GPSX": 6515238.42833333,
        "GPSY": 1736928.54583333,
        "HOMEBASED": "Yes",
        "INACTVDTTM": "2003-08-12T00:00:00.000Z",
        "INSPECTORNAME": "Aswiege",
        "ISSDTTM": "2002-08-26T00:00:00.000Z",
        "LICCATDESC": "Employment Agent",
        "LICENSEDTTM": "2002-08-26T00:00:00.000Z",
        "LICENSENO": "BU20238250",
        "LICENSETYPE": "BU",
        "LICSTATUS": "Inactive",
        "MILESTONE": "Closed",
        "MILESTONEDATE": "2003-08-14T00:00:00.000Z",
        "NONPROFIT": null,
        "NUMBOOTHS": null,
        "NUMEMP": 0,
        "NUMSEATS": 0,
        "NUMSELLINGDAYS": null,
        "NUMSTANDS": 0,
        "NUMUNITS": 0,
        "NUMVEH": 0,
        "OBJECTID": 28570,
        "OUTSIDECITY": "No",
        "PRODUCTTYPES": null,
        "PROPERTYTYPE": "RES",
        "SEPEVENTNAME": null,
        "SITELOCATION": "231  REDONDO AVE 14",
        "STATELICNO": null,
        "TYPEOFBUSINESS": "Employment Agent",
        "ZIP": "90803"
    },
    "type": "Feature"
}