{
    "geometry": {
        "coordinates": [
            -118.22058967510887,
            33.784414755176726
        ],
        "type": "Point"
    },
    "properties": {
        "APPLICATIONREASONDESC": "New License",
        "BIDAREA": null,
        "BLLICEXEMPT": "No",
        "CLASSDESC": "Unique Businesses",
        "COMPANYTYPE": null,
        "CONAME": null,
        "COUNCILDISTRICT": 1,
        "DBANAME": null,
        "EXPDTTM": "2021-09-07T00:00:00.000Z",
        "EXPDTTM_IN": "9/7/2021",
        "FULLNAME": "THREE WAY LLC",
        "GPSX": 6494633.52,
        "GPSY": 1743999.07,
        "HOMEBASED": "No",
        "INACTVDTTM": "2021-09-07T00:00:00.000Z",
        "INSPECTORNAME": "LOVOSS",
        "ISSDTTM": null,
        "LICCATDESC": "Medical MJ Collective",
        "LICENSEDTTM": "2013-08-16T00:00:00.000Z",
        "LICENSENO": "MJ21000790",
        "LICENSETYPE": "BU",
        "LICSTATUS": "Inactive",
        "MILESTONE": "Closed",
        "MILESTONEDATE": "2015-06-22T00:00:00.000Z",
        "NONPROFIT": null,
        "NUMBOOTHS": null,
        "NUMEMP": 0,
        "NUMSEATS": 0,
        "NUMSELLINGDAYS": null,
        "NUMSTANDS": 0,
        "NUMUNITS": 0,
        "NUMVEH": 0,
        "OBJECTID": 72500,
        "OUTSIDECITY": "No",
        "PRODUCTTYPES": null,
        "PROPERTYTYPE": "COM",
        "SEPEVENTNAME": null,
        "SITELOCATION": "2130  COWLES ST",
        "STATELICNO": null,
        "TYPEOFBUSINESS": "Medical MJ Collective",
        "ZIP": "90813"
    },
    "type": "Feature"
}