{
    "geometry": {
        "coordinates": [
            -118.14239647977159,
            33.81541030467614
        ],
        "type": "Point"
    },
    "properties": {
        "APPLICATIONREASONDESC": "New License",
        "BIDAREA": null,
        "BLLICEXEMPT": "No",
        "CLASSDESC": "Services",
        "COMPANYTYPE": "CORP",
        "CONAME": null,
        "COUNCILDISTRICT": 5,
        "DBANAME": null,
        "EXPDTTM": "2013-12-19T00:00:00.000Z",
        "EXPDTTM_IN": "12/19/2013",
        "FULLNAME": "SOCAL JET SERVICES INC",
        "GPSX": 6518410.95416666,
        "GPSY": 1755236.285,
        "HOMEBASED": "No",
        "INACTVDTTM": "2013-12-19T00:00:00.000Z",
        "INSPECTORNAME": "RAGEHRI",
        "ISSDTTM": "2009-09-19T00:00:00.000Z",
        "LICCATDESC": "Aircraft Repair/Repair",
        "LICENSEDTTM": "2010-06-14T00:00:00.000Z",
        "LICENSENO": "BU21018960",
        "LICENSETYPE": "BU",
        "LICSTATUS": "Inactive",
        "MILESTONE": "Closed",
        "MILESTONEDATE": "2013-12-09T00:00:00.000Z",
        "NONPROFIT": null,
        "NUMBOOTHS": null,
        "NUMEMP": 3,
        "NUMSEATS": 0,
        "NUMSELLINGDAYS": null,
        "NUMSTANDS": 0,
        "NUMUNITS": 0,
        "NUMVEH": 0,
        "OBJECTID": 68504,
        "OUTSIDECITY": "No",
        "PRODUCTTYPES": null,
        "PROPERTYTYPE": "COM",
        "SEPEVENTNAME": null,
        "SITELOCATION": "4310  DONALD DOUGLAS DR",
        "STATELICNO": null,
        "TYPEOFBUSINESS": "Aircraft Repair",
        "ZIP": "90808"
    },
    "type": "Feature"
}