{
    "geometry": {
        "coordinates": [
            -118.15581956376617,
            33.763860961588385
        ],
        "type": "Point"
    },
    "properties": {
        "APPLICATIONREASONDESC": "New License",
        "BIDAREA": null,
        "BLLICEXEMPT": "No",
        "CLASSDESC": "Services",
        "COMPANYTYPE": "SOLE",
        "CONAME": null,
        "COUNCILDISTRICT": 3,
        "DBANAME": "MARCO PIZZO DESIGN STUDIO",
        "EXPDTTM": "2017-03-15T00:00:00.000Z",
        "EXPDTTM_IN": "3/15/2017",
        "FULLNAME": "MARCO PIZZO",
        "GPSX": 6514304.35166667,
        "GPSY": 1736482.1125,
        "HOMEBASED": "Yes",
        "INACTVDTTM": null,
        "INSPECTORNAME": "Aswiege",
        "ISSDTTM": "2003-02-26T00:00:00.000Z",
        "LICCATDESC": "Interior Design",
        "LICENSEDTTM": "2003-02-26T00:00:00.000Z",
        "LICENSENO": "BU20309250",
        "LICENSETYPE": "BU",
        "LICSTATUS": "Active",
        "MILESTONE": "Renewed",
        "MILESTONEDATE": "2016-03-11T00:00:00.000Z",
        "NONPROFIT": null,
        "NUMBOOTHS": null,
        "NUMEMP": 0,
        "NUMSEATS": 0,
        "NUMSELLINGDAYS": null,
        "NUMSTANDS": 0,
        "NUMUNITS": 0,
        "NUMVEH": 0,
        "OBJECTID": 85656,
        "OUTSIDECITY": "No",
        "PRODUCTTYPES": null,
        "PROPERTYTYPE": "RES",
        "SEPEVENTNAME": null,
        "SITELOCATION": "117  PALOMA AVE",
        "STATELICNO": null,
        "TYPEOFBUSINESS": "Interior Design",
        "ZIP": "90803"
    },
    "type": "Feature"
}