{
    "geometry": {
        "coordinates": [
            -118.11213753964253,
            33.831213188762895
        ],
        "type": "Point"
    },
    "properties": {
        "APPLICATIONREASONDESC": "New License",
        "BIDAREA": null,
        "BLLICEXEMPT": "No",
        "CLASSDESC": "Retailing",
        "COMPANYTYPE": "CORP",
        "CONAME": null,
        "COUNCILDISTRICT": 5,
        "DBANAME": "EAST LONG BEACH PONY BASEBALL",
        "EXPDTTM": "2015-03-11T00:00:00.000Z",
        "EXPDTTM_IN": "3/11/2015",
        "FULLNAME": "EAST LONG BEACH PONY BASEBALL",
        "GPSX": 6527609.11,
        "GPSY": 1760975.73,
        "HOMEBASED": "No",
        "INACTVDTTM": null,
        "INSPECTORNAME": "RAGEHRI",
        "ISSDTTM": "2003-03-10T00:00:00.000Z",
        "LICCATDESC": "Restaurant & Ready to Eat Foods",
        "LICENSEDTTM": "2003-03-11T00:00:00.000Z",
        "LICENSENO": "BU20311630",
        "LICENSETYPE": "BU",
        "LICSTATUS": "CollcInBus",
        "MILESTONE": "Pre-Collections",
        "MILESTONEDATE": "2016-04-11T00:00:00.000Z",
        "NONPROFIT": null,
        "NUMBOOTHS": null,
        "NUMEMP": 1,
        "NUMSEATS": 0,
        "NUMSELLINGDAYS": null,
        "NUMSTANDS": 0,
        "NUMUNITS": 0,
        "NUMVEH": 0,
        "OBJECTID": 84513,
        "OUTSIDECITY": "No",
        "PRODUCTTYPES": null,
        "PROPERTYTYPE": "COM",
        "SEPEVENTNAME": null,
        "SITELOCATION": "6150 E CARSON ST",
        "STATELICNO": null,
        "TYPEOFBUSINESS": "Restaurant & Ready to Eat Foods",
        "ZIP": "90808"
    },
    "type": "Feature"
}