{
    "geometry": {
        "coordinates": [
            -118.17576531540978,
            33.78236697266487
        ],
        "type": "Point"
    },
    "properties": {
        "APPLICATIONREASONDESC": "New License",
        "BIDAREA": null,
        "BLLICEXEMPT": "No",
        "CLASSDESC": "Retailing",
        "COMPANYTYPE": "SOLE",
        "CONAME": null,
        "COUNCILDISTRICT": 6,
        "DBANAME": "ALL UNITED CELL SERVICES",
        "EXPDTTM": "2015-09-01T00:00:00.000Z",
        "EXPDTTM_IN": "9/1/2015",
        "FULLNAME": "ALVIN PHEASA UNG",
        "GPSX": 6508253.5,
        "GPSY": 1743226.97,
        "HOMEBASED": "No",
        "INACTVDTTM": "2015-09-01T00:00:00.000Z",
        "INSPECTORNAME": "Aswiege",
        "ISSDTTM": "2013-08-16T00:00:00.000Z",
        "LICCATDESC": "Retail Sales",
        "LICENSEDTTM": "2013-08-16T00:00:00.000Z",
        "LICENSENO": "BU21324640",
        "LICENSETYPE": "BU",
        "LICSTATUS": "Inactive",
        "MILESTONE": "Closed",
        "MILESTONEDATE": "2015-07-28T00:00:00.000Z",
        "NONPROFIT": null,
        "NUMBOOTHS": null,
        "NUMEMP": 2,
        "NUMSEATS": 0,
        "NUMSELLINGDAYS": null,
        "NUMSTANDS": 0,
        "NUMUNITS": 0,
        "NUMVEH": 0,
        "OBJECTID": 60233,
        "OUTSIDECITY": "No",
        "PRODUCTTYPES": null,
        "PROPERTYTYPE": "COM",
        "SEPEVENTNAME": null,
        "SITELOCATION": "1218 E ANAHEIM ST",
        "STATELICNO": null,
        "TYPEOFBUSINESS": "Retail Sales",
        "ZIP": "90813"
    },
    "type": "Feature"
}