{
    "geometry": {
        "coordinates": [
            -118.18463706452314,
            33.832385055354756
        ],
        "type": "Point"
    },
    "properties": {
        "APPLICATIONREASONDESC": "Change of Address",
        "BIDAREA": "BIXBY",
        "BLLICEXEMPT": "No",
        "CLASSDESC": "Services",
        "COMPANYTYPE": "SOLE",
        "CONAME": null,
        "COUNCILDISTRICT": 8,
        "DBANAME": "ASSOCIATED BUSINESS SERVICE",
        "EXPDTTM": "2003-04-23T00:00:00.000Z",
        "EXPDTTM_IN": "4/23/2003",
        "FULLNAME": "MARIE ROUNDS",
        "GPSX": 6505590.91166667,
        "GPSY": 1761434.7075,
        "HOMEBASED": "No",
        "INACTVDTTM": "2003-04-23T00:00:00.000Z",
        "INSPECTORNAME": "EURODRI",
        "ISSDTTM": "1995-06-26T00:00:00.000Z",
        "LICCATDESC": "Tax Preparation",
        "LICENSEDTTM": "2001-01-05T00:00:00.000Z",
        "LICENSENO": "BU20100730",
        "LICENSETYPE": "BU",
        "LICSTATUS": "Inactive",
        "MILESTONE": "Closed",
        "MILESTONEDATE": "2003-06-13T00:00:00.000Z",
        "NONPROFIT": null,
        "NUMBOOTHS": null,
        "NUMEMP": 2,
        "NUMSEATS": 0,
        "NUMSELLINGDAYS": null,
        "NUMSTANDS": 0,
        "NUMUNITS": 0,
        "NUMVEH": 0,
        "OBJECTID": 9600,
        "OUTSIDECITY": "No",
        "PRODUCTTYPES": null,
        "PROPERTYTYPE": "COM",
        "SEPEVENTNAME": null,
        "SITELOCATION": "4130  ATLANTIC AVE 111",
        "STATELICNO": null,
        "TYPEOFBUSINESS": "Tax Preparation",
        "ZIP": "90807"
    },
    "type": "Feature"
}