{
    "geometry": {
        "coordinates": [
            -118.19597991543837,
            33.785795810905064
        ],
        "type": "Point"
    },
    "properties": {
        "APPLICATIONREASONDESC": "Change of Ownership",
        "BIDAREA": null,
        "BLLICEXEMPT": "No",
        "CLASSDESC": "Rental ??? Residential Property",
        "COMPANYTYPE": "SOLE",
        "CONAME": null,
        "COUNCILDISTRICT": 1,
        "DBANAME": null,
        "EXPDTTM": "2005-07-01T00:00:00.000Z",
        "EXPDTTM_IN": "7/1/2005",
        "FULLNAME": "SADE B OLATUBOSUN",
        "GPSX": 6502112.94333333,
        "GPSY": 1744486.1775,
        "HOMEBASED": "No",
        "INACTVDTTM": "2005-07-01T00:00:00.000Z",
        "INSPECTORNAME": "LOVOSS",
        "ISSDTTM": "1998-02-05T00:00:00.000Z",
        "LICCATDESC": "Apartment House",
        "LICENSEDTTM": "2004-07-23T00:00:00.000Z",
        "LICENSENO": "BU03035604",
        "LICENSETYPE": "BU",
        "LICSTATUS": "Inactive",
        "MILESTONE": "Closed",
        "MILESTONEDATE": "2005-10-10T00:00:00.000Z",
        "NONPROFIT": null,
        "NUMBOOTHS": null,
        "NUMEMP": 0,
        "NUMSEATS": 0,
        "NUMSELLINGDAYS": null,
        "NUMSTANDS": 0,
        "NUMUNITS": 4,
        "NUMVEH": 0,
        "OBJECTID": 146413,
        "OUTSIDECITY": "No",
        "PRODUCTTYPES": null,
        "PROPERTYTYPE": "COM",
        "SEPEVENTNAME": null,
        "SITELOCATION": "1480  CHESTNUT AVE",
        "STATELICNO": null,
        "TYPEOFBUSINESS": "Apartment House",
        "ZIP": "90813"
    },
    "type": "Feature"
}