{
    "geometry": {
        "coordinates": [
            -118.16429654949359,
            33.785059547319
        ],
        "type": "Point"
    },
    "properties": {
        "APPLICATIONREASONDESC": "Change of Ownership",
        "BIDAREA": null,
        "BLLICEXEMPT": "No",
        "CLASSDESC": "Rental ??? Residential Property",
        "COMPANYTYPE": "SOLE",
        "CONAME": null,
        "COUNCILDISTRICT": 4,
        "DBANAME": null,
        "EXPDTTM": "2012-07-01T00:00:00.000Z",
        "EXPDTTM_IN": "7/1/2012",
        "FULLNAME": "VERN & GENEVA DEBUHR",
        "GPSX": 6511740.33166667,
        "GPSY": 1744200.97666667,
        "HOMEBASED": "No",
        "INACTVDTTM": "2012-07-01T00:00:00.000Z",
        "INSPECTORNAME": "RAGEHRI",
        "ISSDTTM": "1994-09-19T00:00:00.000Z",
        "LICCATDESC": "Apartment House",
        "LICENSEDTTM": "2004-05-27T00:00:00.000Z",
        "LICENSENO": "BU94050382",
        "LICENSETYPE": "BU",
        "LICSTATUS": "Inactive",
        "MILESTONE": "Closed",
        "MILESTONEDATE": "2011-07-08T00:00:00.000Z",
        "NONPROFIT": null,
        "NUMBOOTHS": null,
        "NUMEMP": 0,
        "NUMSEATS": 0,
        "NUMSELLINGDAYS": null,
        "NUMSTANDS": 0,
        "NUMUNITS": 4,
        "NUMVEH": 0,
        "OBJECTID": 148406,
        "OUTSIDECITY": "No",
        "PRODUCTTYPES": null,
        "PROPERTYTYPE": "COM",
        "SEPEVENTNAME": null,
        "SITELOCATION": "2300  SPAULDING ST  2300/02 2004 A/B Spaulding St",
        "STATELICNO": null,
        "TYPEOFBUSINESS": "Apartment House",
        "ZIP": "90804"
    },
    "type": "Feature"
}