{
    "geometry": {
        "coordinates": [
            -118.19464758277456,
            33.76663700012554
        ],
        "type": "Point"
    },
    "properties": {
        "APPLICATIONREASONDESC": "Change of Ownership",
        "BIDAREA": "DOWNTOWN",
        "BLLICEXEMPT": "No",
        "CLASSDESC": "Retailing",
        "COMPANYTYPE": "PARTNER",
        "CONAME": null,
        "COUNCILDISTRICT": 2,
        "DBANAME": "THE WINE BAR/VILLAGE TASTING ROOM",
        "EXPDTTM": "2017-05-28T00:00:00.000Z",
        "EXPDTTM_IN": "5/28/2017",
        "FULLNAME": "STUART K & LISA A SMITH",
        "GPSX": 6502504.30583333,
        "GPSY": 1737512.96666667,
        "HOMEBASED": "No",
        "INACTVDTTM": null,
        "INSPECTORNAME": "LOVOSS",
        "ISSDTTM": "2004-03-29T00:00:00.000Z",
        "LICCATDESC": "Bar, Tavern, Lounge",
        "LICENSEDTTM": "2009-06-22T00:00:00.000Z",
        "LICENSENO": "BU20923700",
        "LICENSETYPE": "BU",
        "LICSTATUS": "Active",
        "MILESTONE": "Renewed",
        "MILESTONEDATE": "2016-06-27T00:00:00.000Z",
        "NONPROFIT": null,
        "NUMBOOTHS": null,
        "NUMEMP": 4,
        "NUMSEATS": 0,
        "NUMSELLINGDAYS": null,
        "NUMSTANDS": 0,
        "NUMUNITS": 0,
        "NUMVEH": 0,
        "OBJECTID": 170717,
        "OUTSIDECITY": "No",
        "PRODUCTTYPES": null,
        "PROPERTYTYPE": "COM",
        "SEPEVENTNAME": null,
        "SITELOCATION": "250 W OCEAN BLVD",
        "STATELICNO": null,
        "TYPEOFBUSINESS": "Bar, Tavern, Lounge",
        "ZIP": "90802"
    },
    "type": "Feature"
}