{
    "geometry": {
        "coordinates": [
            -118.12805323571015,
            33.75874354767355
        ],
        "type": "Point"
    },
    "properties": {
        "APPLICATIONREASONDESC": "New License",
        "BIDAREA": null,
        "BLLICEXEMPT": "No",
        "CLASSDESC": "Rental ??? Residential Property",
        "COMPANYTYPE": "PARTNER",
        "CONAME": null,
        "COUNCILDISTRICT": 3,
        "DBANAME": null,
        "EXPDTTM": "2017-07-01T00:00:00.000Z",
        "EXPDTTM_IN": "7/1/2017",
        "FULLNAME": "A J & RALPH G BURGBACHER",
        "GPSX": 6522741.72,
        "GPSY": 1734607.82,
        "HOMEBASED": "No",
        "INACTVDTTM": null,
        "INSPECTORNAME": "Aswiege",
        "ISSDTTM": "1992-01-29T00:00:00.000Z",
        "LICCATDESC": "Apartment House",
        "LICENSEDTTM": "1992-01-29T00:00:00.000Z",
        "LICENSENO": "BU92004100",
        "LICENSETYPE": "BU",
        "LICSTATUS": "Active",
        "MILESTONE": "Renewed",
        "MILESTONEDATE": "2016-07-12T00:00:00.000Z",
        "NONPROFIT": null,
        "NUMBOOTHS": null,
        "NUMEMP": 0,
        "NUMSEATS": 0,
        "NUMSELLINGDAYS": null,
        "NUMSTANDS": 0,
        "NUMUNITS": 8,
        "NUMVEH": 0,
        "OBJECTID": 57041,
        "OUTSIDECITY": "No",
        "PRODUCTTYPES": null,
        "PROPERTYTYPE": "COM",
        "SEPEVENTNAME": null,
        "SITELOCATION": "5441  SORRENTO DR",
        "STATELICNO": null,
        "TYPEOFBUSINESS": "Apartment House",
        "ZIP": "90803"
    },
    "type": "Feature"
}