{
    "geometry": {
        "coordinates": [
            -118.1652974924032,
            33.782307428600035
        ],
        "type": "Point"
    },
    "properties": {
        "APPLICATIONREASONDESC": "New License",
        "BIDAREA": null,
        "BLLICEXEMPT": "No",
        "CLASSDESC": "Services",
        "COMPANYTYPE": "LLC",
        "CONAME": null,
        "COUNCILDISTRICT": 4,
        "DBANAME": "BLOODCHEK",
        "EXPDTTM": "2012-07-01T00:00:00.000Z",
        "EXPDTTM_IN": "7/1/2012",
        "FULLNAME": "ODYSSEY CLINICAL LABORATORIES",
        "GPSX": 6511434.51916667,
        "GPSY": 1743199.90333333,
        "HOMEBASED": "No",
        "INACTVDTTM": "2012-07-01T00:00:00.000Z",
        "INSPECTORNAME": "RAGEHRI",
        "ISSDTTM": "2011-07-01T00:00:00.000Z",
        "LICCATDESC": "Laboratory - Medical/Dental",
        "LICENSEDTTM": "2011-06-21T00:00:00.000Z",
        "LICENSENO": "BU21120740",
        "LICENSETYPE": "BU",
        "LICSTATUS": "Inactive",
        "MILESTONE": "Closed",
        "MILESTONEDATE": "2011-09-09T00:00:00.000Z",
        "NONPROFIT": null,
        "NUMBOOTHS": null,
        "NUMEMP": 2,
        "NUMSEATS": 0,
        "NUMSELLINGDAYS": null,
        "NUMSTANDS": 0,
        "NUMUNITS": 0,
        "NUMVEH": 0,
        "OBJECTID": 138671,
        "OUTSIDECITY": "No",
        "PRODUCTTYPES": null,
        "PROPERTYTYPE": "COM",
        "SEPEVENTNAME": null,
        "SITELOCATION": "2200 E ANAHEIM ST C",
        "STATELICNO": null,
        "TYPEOFBUSINESS": "Laboratory - Medical/Dental",
        "ZIP": "90804"
    },
    "type": "Feature"
}