{
    "geometry": {
        "coordinates": [
            -118.136728106411,
            33.761372435388466
        ],
        "type": "Point"
    },
    "properties": {
        "APPLICATIONREASONDESC": "New License",
        "BIDAREA": "BELMONT",
        "BLLICEXEMPT": "No",
        "CLASSDESC": "Services",
        "COMPANYTYPE": "LLC",
        "CONAME": null,
        "COUNCILDISTRICT": 3,
        "DBANAME": "AT&T MOBILITY",
        "EXPDTTM": "2017-06-01T00:00:00.000Z",
        "EXPDTTM_IN": "6/1/2017",
        "FULLNAME": "NEW CINGULAR WIRELESS PCS LLC",
        "GPSX": 6520106.08166667,
        "GPSY": 1735568.02166667,
        "HOMEBASED": "No",
        "INACTVDTTM": null,
        "INSPECTORNAME": "Aswiege",
        "ISSDTTM": "2009-06-01T00:00:00.000Z",
        "LICCATDESC": "Communication Facility - Cell Site",
        "LICENSEDTTM": "2010-11-15T00:00:00.000Z",
        "LICENSENO": "BU21036690",
        "LICENSETYPE": "BU",
        "LICSTATUS": "Active",
        "MILESTONE": "Renewed",
        "MILESTONEDATE": "2016-06-27T00:00:00.000Z",
        "NONPROFIT": null,
        "NUMBOOTHS": null,
        "NUMEMP": 0,
        "NUMSEATS": 0,
        "NUMSELLINGDAYS": null,
        "NUMSTANDS": 0,
        "NUMUNITS": 0,
        "NUMVEH": 0,
        "OBJECTID": 128613,
        "OUTSIDECITY": "No",
        "PRODUCTTYPES": null,
        "PROPERTYTYPE": "COM",
        "SEPEVENTNAME": null,
        "SITELOCATION": "4917  2ND ST",
        "STATELICNO": null,
        "TYPEOFBUSINESS": "Communication Facility - Cell Site",
        "ZIP": "90803"
    },
    "type": "Feature"
}