{
    "geometry": {
        "coordinates": [
            -118.19000016589995,
            33.829253435165
        ],
        "type": "Point"
    },
    "properties": {
        "APPLICATIONREASONDESC": "New License",
        "BIDAREA": null,
        "BLLICEXEMPT": "No",
        "CLASSDESC": "Miscellaneous Mobile",
        "COMPANYTYPE": "SOLE",
        "CONAME": null,
        "COUNCILDISTRICT": 8,
        "DBANAME": "CAL CLEAN",
        "EXPDTTM": "2016-01-01T00:00:00.000Z",
        "EXPDTTM_IN": "1/1/2016",
        "FULLNAME": "DENNIS GUILLEN",
        "GPSX": 6503959.9425,
        "GPSY": 1760298.06666667,
        "HOMEBASED": "Yes",
        "INACTVDTTM": "2016-03-09T00:00:00.000Z",
        "INSPECTORNAME": "EURODRI",
        "ISSDTTM": "2015-07-13T00:00:00.000Z",
        "LICCATDESC": "Janitorial Service",
        "LICENSEDTTM": "2015-07-13T00:00:00.000Z",
        "LICENSENO": "BU21520740",
        "LICENSETYPE": "BU",
        "LICSTATUS": "Expired",
        "MILESTONE": "Closed",
        "MILESTONEDATE": "2016-03-09T00:00:00.000Z",
        "NONPROFIT": null,
        "NUMBOOTHS": null,
        "NUMEMP": 0,
        "NUMSEATS": 0,
        "NUMSELLINGDAYS": null,
        "NUMSTANDS": 0,
        "NUMUNITS": 0,
        "NUMVEH": 1,
        "OBJECTID": 146568,
        "OUTSIDECITY": "No",
        "PRODUCTTYPES": null,
        "PROPERTYTYPE": "RES",
        "SEPEVENTNAME": null,
        "SITELOCATION": "3909  VIRGINIA RD B",
        "STATELICNO": null,
        "TYPEOFBUSINESS": "Janitorial Service",
        "ZIP": "90807"
    },
    "type": "Feature"
}