{
    "geometry": {
        "coordinates": [
            -118.16179552860476,
            33.857776822077334
        ],
        "type": "Point"
    },
    "properties": {
        "APPLICATIONREASONDESC": "New License",
        "BIDAREA": null,
        "BLLICEXEMPT": "No",
        "CLASSDESC": "Miscellaneous Mobile",
        "COMPANYTYPE": "SOLE",
        "CONAME": null,
        "COUNCILDISTRICT": 8,
        "DBANAME": "AMELIA FLORES",
        "EXPDTTM": "2005-01-01T00:00:00.000Z",
        "EXPDTTM_IN": "1/1/2005",
        "FULLNAME": "AMELIA FLORES",
        "GPSX": 6512542.93666667,
        "GPSY": 1770663.45166667,
        "HOMEBASED": "No",
        "INACTVDTTM": "2005-01-01T00:00:00.000Z",
        "INSPECTORNAME": "EURODRI",
        "ISSDTTM": "2003-06-26T00:00:00.000Z",
        "LICCATDESC": "Janitorial Service",
        "LICENSEDTTM": "2003-06-26T00:00:00.000Z",
        "LICENSENO": "BU20330350",
        "LICENSETYPE": "BU",
        "LICSTATUS": "Inactive",
        "MILESTONE": "Closed",
        "MILESTONEDATE": "2004-01-05T00:00:00.000Z",
        "NONPROFIT": null,
        "NUMBOOTHS": null,
        "NUMEMP": 0,
        "NUMSEATS": 0,
        "NUMSELLINGDAYS": null,
        "NUMSTANDS": 0,
        "NUMUNITS": 0,
        "NUMVEH": 1,
        "OBJECTID": 154956,
        "OUTSIDECITY": "No",
        "PRODUCTTYPES": null,
        "PROPERTYTYPE": "COM",
        "SEPEVENTNAME": null,
        "SITELOCATION": "5599  LANGPORT AVE",
        "STATELICNO": null,
        "TYPEOFBUSINESS": "Janitorial Service",
        "ZIP": "90805"
    },
    "type": "Feature"
}