{
    "geometry": {
        "coordinates": [
            -118.1339244755328,
            33.7601747308158
        ],
        "type": "Point"
    },
    "properties": {
        "APPLICATIONREASONDESC": "New License",
        "BIDAREA": "BELMONT",
        "BLLICEXEMPT": "No",
        "CLASSDESC": "Services",
        "COMPANYTYPE": "SOLE",
        "CONAME": null,
        "COUNCILDISTRICT": 3,
        "DBANAME": "Belmont Shore Spa",
        "EXPDTTM": "2017-07-01T00:00:00.000Z",
        "EXPDTTM_IN": "7/1/2017",
        "FULLNAME": "MARCOS MOLINA",
        "GPSX": 6520957.70666667,
        "GPSY": 1735130.995,
        "HOMEBASED": "No",
        "INACTVDTTM": null,
        "INSPECTORNAME": "Aswiege",
        "ISSDTTM": "2016-07-01T00:00:00.000Z",
        "LICCATDESC": "Massage/Body Wrap Tech",
        "LICENSEDTTM": "2016-06-13T00:00:00.000Z",
        "LICENSENO": "BU21603667",
        "LICENSETYPE": "BU",
        "LICSTATUS": "Active",
        "MILESTONE": "Issued",
        "MILESTONEDATE": "2016-09-02T00:00:00.000Z",
        "NONPROFIT": null,
        "NUMBOOTHS": null,
        "NUMEMP": 0,
        "NUMSEATS": 0,
        "NUMSELLINGDAYS": null,
        "NUMSTANDS": 0,
        "NUMUNITS": 0,
        "NUMVEH": 0,
        "OBJECTID": 88189,
        "OUTSIDECITY": "No",
        "PRODUCTTYPES": null,
        "PROPERTYTYPE": "COM",
        "SEPEVENTNAME": null,
        "SITELOCATION": "5237  2ND ST",
        "STATELICNO": null,
        "TYPEOFBUSINESS": "Massage/Body Wrap Tech",
        "ZIP": "90803"
    },
    "type": "Feature"
}