{
    "geometry": {
        "coordinates": [
            -118.19761102644513,
            33.853992869225124
        ],
        "type": "Point"
    },
    "properties": {
        "APPLICATIONREASONDESC": "New License",
        "BIDAREA": null,
        "BLLICEXEMPT": "No",
        "CLASSDESC": "Retailing",
        "COMPANYTYPE": "SOLE",
        "CONAME": null,
        "COUNCILDISTRICT": 8,
        "DBANAME": "PARRELL FRAGRANCE",
        "EXPDTTM": "2000-09-01T00:00:00.000Z",
        "EXPDTTM_IN": "9/1/2000",
        "FULLNAME": "DARRELL RUCKER",
        "GPSX": 6501666.08,
        "GPSY": 1769305.82,
        "HOMEBASED": "Yes",
        "INACTVDTTM": "2015-12-03T00:00:00.000Z",
        "INSPECTORNAME": "EURODRI",
        "ISSDTTM": "2000-07-31T00:00:00.000Z",
        "LICCATDESC": "Home Crafts (including ceramics with kiln up to 6 cubic feet)",
        "LICENSEDTTM": "2000-07-31T00:00:00.000Z",
        "LICENSENO": "BU20031080",
        "LICENSETYPE": "BU",
        "LICSTATUS": "Inactive",
        "MILESTONE": "Closed",
        "MILESTONEDATE": "2015-12-03T00:00:00.000Z",
        "NONPROFIT": null,
        "NUMBOOTHS": null,
        "NUMEMP": 0,
        "NUMSEATS": 0,
        "NUMSELLINGDAYS": null,
        "NUMSTANDS": 0,
        "NUMUNITS": 0,
        "NUMVEH": 0,
        "OBJECTID": 8220,
        "OUTSIDECITY": "No",
        "PRODUCTTYPES": null,
        "PROPERTYTYPE": "RES",
        "SEPEVENTNAME": null,
        "SITELOCATION": "46 W MARKET ST",
        "STATELICNO": null,
        "TYPEOFBUSINESS": "Home Crafts (including ceramics with kiln up to 6 cubic feet)",
        "ZIP": "90805"
    },
    "type": "Feature"
}