{
    "geometry": {
        "coordinates": [
            -118.1777026079171,
            33.82526867424192
        ],
        "type": "Point"
    },
    "properties": {
        "APPLICATIONREASONDESC": "New License",
        "BIDAREA": null,
        "BLLICEXEMPT": "No",
        "CLASSDESC": "Services",
        "COMPANYTYPE": "CORP",
        "CONAME": null,
        "COUNCILDISTRICT": 7,
        "DBANAME": null,
        "EXPDTTM": "2016-12-24T00:00:00.000Z",
        "EXPDTTM_IN": "12/24/2016",
        "FULLNAME": "DISCOUNT PEST SUPPLY",
        "GPSX": 6507692.38083333,
        "GPSY": 1758841.07833333,
        "HOMEBASED": "Yes",
        "INACTVDTTM": null,
        "INSPECTORNAME": "EURODRI",
        "ISSDTTM": "2010-12-27T00:00:00.000Z",
        "LICCATDESC": "Internet Sales/Service",
        "LICENSEDTTM": "2010-12-27T00:00:00.000Z",
        "LICENSENO": "BU21040740",
        "LICENSETYPE": "BU",
        "LICSTATUS": "Active",
        "MILESTONE": "Renewed",
        "MILESTONEDATE": "2015-12-24T00:00:00.000Z",
        "NONPROFIT": null,
        "NUMBOOTHS": null,
        "NUMEMP": 2,
        "NUMSEATS": 0,
        "NUMSELLINGDAYS": null,
        "NUMSTANDS": 0,
        "NUMUNITS": 0,
        "NUMVEH": 0,
        "OBJECTID": 3961,
        "OUTSIDECITY": "No",
        "PRODUCTTYPES": null,
        "PROPERTYTYPE": "RES",
        "SEPEVENTNAME": null,
        "SITELOCATION": "3729  CERRITOS AVE",
        "STATELICNO": null,
        "TYPEOFBUSINESS": "Internet Sales/Service",
        "ZIP": "90807"
    },
    "type": "Feature"
}