{
    "geometry": {
        "coordinates": [
            -118.13888595535921,
            33.75842685841036
        ],
        "type": "Point"
    },
    "properties": {
        "APPLICATIONREASONDESC": "Change of Ownership",
        "BIDAREA": null,
        "BLLICEXEMPT": "No",
        "CLASSDESC": "Services",
        "COMPANYTYPE": "SOLE",
        "CONAME": null,
        "COUNCILDISTRICT": 3,
        "DBANAME": "JAMES HUTH ENTERPRISES",
        "EXPDTTM": "2008-12-17T00:00:00.000Z",
        "EXPDTTM_IN": "12/17/2008",
        "FULLNAME": "JAMES HUTH",
        "GPSX": 6519448.69,
        "GPSY": 1734496.94,
        "HOMEBASED": "Yes",
        "INACTVDTTM": "2008-12-17T00:00:00.000Z",
        "INSPECTORNAME": "Aswiege",
        "ISSDTTM": "2006-04-12T00:00:00.000Z",
        "LICCATDESC": "Consulting",
        "LICENSEDTTM": "2006-04-12T00:00:00.000Z",
        "LICENSENO": "BU20619550",
        "LICENSETYPE": "BU",
        "LICSTATUS": "Inactive",
        "MILESTONE": "Closed",
        "MILESTONEDATE": "2009-01-26T00:00:00.000Z",
        "NONPROFIT": null,
        "NUMBOOTHS": null,
        "NUMEMP": 2,
        "NUMSEATS": 0,
        "NUMSELLINGDAYS": null,
        "NUMSTANDS": 0,
        "NUMUNITS": 0,
        "NUMVEH": 0,
        "OBJECTID": 54501,
        "OUTSIDECITY": "No",
        "PRODUCTTYPES": null,
        "PROPERTYTYPE": "RES",
        "SEPEVENTNAME": null,
        "SITELOCATION": "104  ST JOSEPH AVE",
        "STATELICNO": null,
        "TYPEOFBUSINESS": "Consulting",
        "ZIP": "90803"
    },
    "type": "Feature"
}