{
    "geometry": {
        "coordinates": [
            -118.11458631190534,
            33.77295884744261
        ],
        "type": "Point"
    },
    "properties": {
        "APPLICATIONREASONDESC": "New License",
        "BIDAREA": null,
        "BLLICEXEMPT": "No",
        "CLASSDESC": "Services",
        "COMPANYTYPE": "PARTNER",
        "CONAME": null,
        "COUNCILDISTRICT": 3,
        "DBANAME": "DIFFERENCE MAKERS PUBLISHERS",
        "EXPDTTM": "2017-05-11T00:00:00.000Z",
        "EXPDTTM_IN": "5/11/2017",
        "FULLNAME": "NGIABI & DARLENE GICUHI",
        "GPSX": 6526841.22,
        "GPSY": 1739776.23583333,
        "HOMEBASED": "Yes",
        "INACTVDTTM": null,
        "INSPECTORNAME": "Aswiege",
        "ISSDTTM": "2009-05-04T00:00:00.000Z",
        "LICCATDESC": "Writing",
        "LICENSEDTTM": "2009-05-04T00:00:00.000Z",
        "LICENSENO": "BU20917150",
        "LICENSETYPE": "BU",
        "LICSTATUS": "Active",
        "MILESTONE": "Renewed",
        "MILESTONEDATE": "2016-05-09T00:00:00.000Z",
        "NONPROFIT": null,
        "NUMBOOTHS": null,
        "NUMEMP": 2,
        "NUMSEATS": 0,
        "NUMSELLINGDAYS": null,
        "NUMSTANDS": 0,
        "NUMUNITS": 0,
        "NUMVEH": 0,
        "OBJECTID": 47797,
        "OUTSIDECITY": "No",
        "PRODUCTTYPES": null,
        "PROPERTYTYPE": "RES",
        "SEPEVENTNAME": null,
        "SITELOCATION": "450  MEDFORD CT",
        "STATELICNO": null,
        "TYPEOFBUSINESS": "Writing",
        "ZIP": "90803"
    },
    "type": "Feature"
}