{
    "geometry": {
        "coordinates": [
            -118.11733262530122,
            33.76649673537371
        ],
        "type": "Point"
    },
    "properties": {
        "APPLICATIONREASONDESC": "New License",
        "BIDAREA": null,
        "BLLICEXEMPT": "No",
        "CLASSDESC": "Services",
        "COMPANYTYPE": "SOLE",
        "CONAME": "MARIA L CORKETT",
        "COUNCILDISTRICT": 3,
        "DBANAME": "MALOU HAIR STUDIO",
        "EXPDTTM": "2017-04-22T00:00:00.000Z",
        "EXPDTTM_IN": "4/22/2017",
        "FULLNAME": "MARIA L BURNS",
        "GPSX": 6526003.80666667,
        "GPSY": 1737425.45166667,
        "HOMEBASED": "No",
        "INACTVDTTM": null,
        "INSPECTORNAME": "Aswiege",
        "ISSDTTM": "2015-04-21T00:00:00.000Z",
        "LICCATDESC": "Barber/Beauty (booth )",
        "LICENSEDTTM": "2015-04-21T00:00:00.000Z",
        "LICENSENO": "BU21511740",
        "LICENSETYPE": "BU",
        "LICSTATUS": "Active",
        "MILESTONE": "Renewed",
        "MILESTONEDATE": "2016-05-17T00:00:00.000Z",
        "NONPROFIT": null,
        "NUMBOOTHS": null,
        "NUMEMP": 0,
        "NUMSEATS": 0,
        "NUMSELLINGDAYS": null,
        "NUMSTANDS": 0,
        "NUMUNITS": 0,
        "NUMVEH": 0,
        "OBJECTID": 9949,
        "OUTSIDECITY": "No",
        "PRODUCTTYPES": null,
        "PROPERTYTYPE": "COM",
        "SEPEVENTNAME": null,
        "SITELOCATION": "6232 E PACIFIC COAST HWY",
        "STATELICNO": null,
        "TYPEOFBUSINESS": "Barber/Beauty (booth )",
        "ZIP": "90803"
    },
    "type": "Feature"
}