{
    "geometry": {
        "coordinates": [
            -118.19727599043826,
            33.87457291305263
        ],
        "type": "Point"
    },
    "properties": {
        "APPLICATIONREASONDESC": "Change of Ownership",
        "BIDAREA": null,
        "BLLICEXEMPT": "No",
        "CLASSDESC": "Services",
        "COMPANYTYPE": "SOLE",
        "CONAME": null,
        "COUNCILDISTRICT": 9,
        "DBANAME": "K & C NAILS SPA",
        "EXPDTTM": "2009-07-23T00:00:00.000Z",
        "EXPDTTM_IN": "7/23/2009",
        "FULLNAME": "KIM L HOANG",
        "GPSX": 6501782.50583333,
        "GPSY": 1776795.1925,
        "HOMEBASED": "No",
        "INACTVDTTM": "2009-07-23T00:00:00.000Z",
        "INSPECTORNAME": "EURODRI",
        "ISSDTTM": "2009-07-23T00:00:00.000Z",
        "LICCATDESC": "Nails/Manicure Shop",
        "LICENSEDTTM": "2009-07-23T00:00:00.000Z",
        "LICENSENO": "BU20928010",
        "LICENSETYPE": "BU",
        "LICSTATUS": "Inactive",
        "MILESTONE": "Closed",
        "MILESTONEDATE": "2009-10-20T00:00:00.000Z",
        "NONPROFIT": null,
        "NUMBOOTHS": null,
        "NUMEMP": 2,
        "NUMSEATS": 0,
        "NUMSELLINGDAYS": null,
        "NUMSTANDS": 0,
        "NUMUNITS": 0,
        "NUMVEH": 0,
        "OBJECTID": 48448,
        "OUTSIDECITY": "No",
        "PRODUCTTYPES": null,
        "PROPERTYTYPE": "COM",
        "SEPEVENTNAME": null,
        "SITELOCATION": "295 E ARTESIA BLVD",
        "STATELICNO": null,
        "TYPEOFBUSINESS": "Nails/Manicure Shop",
        "ZIP": "90805"
    },
    "type": "Feature"
}