{
    "geometry": {
        "coordinates": [
            -118.10729172914591,
            33.75288080363109
        ],
        "type": "Point"
    },
    "properties": {
        "APPLICATIONREASONDESC": "New License",
        "BIDAREA": null,
        "BLLICEXEMPT": "No",
        "CLASSDESC": "Services",
        "COMPANYTYPE": "CORP",
        "CONAME": null,
        "COUNCILDISTRICT": 3,
        "DBANAME": "PRUDENTIAL SECURITIES",
        "EXPDTTM": "2005-06-01T00:00:00.000Z",
        "EXPDTTM_IN": "6/1/2005",
        "FULLNAME": "PRUDENTIAL SECURITIES INCORPORATED",
        "GPSX": 6529050.41333333,
        "GPSY": 1732466.8075,
        "HOMEBASED": "No",
        "INACTVDTTM": "2005-06-01T00:00:00.000Z",
        "INSPECTORNAME": "Aswiege",
        "ISSDTTM": "1992-08-19T00:00:00.000Z",
        "LICCATDESC": "Stocks & Bonds Broker",
        "LICENSEDTTM": "1992-08-19T00:00:00.000Z",
        "LICENSENO": "BU92038140",
        "LICENSETYPE": "BU",
        "LICSTATUS": "Inactive",
        "MILESTONE": "Closed",
        "MILESTONEDATE": "2004-08-17T00:00:00.000Z",
        "NONPROFIT": null,
        "NUMBOOTHS": null,
        "NUMEMP": 24,
        "NUMSEATS": 0,
        "NUMSELLINGDAYS": null,
        "NUMSTANDS": 0,
        "NUMUNITS": 0,
        "NUMVEH": 0,
        "OBJECTID": 172986,
        "OUTSIDECITY": "No",
        "PRODUCTTYPES": null,
        "PROPERTYTYPE": "COM",
        "SEPEVENTNAME": null,
        "SITELOCATION": "6700 E PACIFIC COAST HWY 170",
        "STATELICNO": null,
        "TYPEOFBUSINESS": "Stocks & Bonds Broker",
        "ZIP": "90803"
    },
    "type": "Feature"
}